atams/__init__.py
atams/api/__init__.py
atams/api/health.py
atams/cli/__init__.py
atams/cli/main.py
atams/cli/commands/__init__.py
atams/cli/commands/generate.py
atams/cli/commands/init_cmd.py
atams/cli/templates/endpoint.jinja2
atams/cli/templates/model.jinja2
atams/cli/templates/repository.jinja2
atams/cli/templates/schema.jinja2
atams/cli/templates/service.jinja2
atams/config/__init__.py
atams/config/base.py
atams/db/__init__.py
atams/db/base.py
atams/db/repository.py
atams/db/session.py
atams/encryption/__init__.py
atams/encryption/response.py
atams/exceptions/__init__.py
atams/exceptions/base.py
atams/exceptions/handlers.py
atams/logging/__init__.py
atams/logging/setup.py
atams/middleware/__init__.py
atams/middleware/rate_limiter.py
atams/middleware/request_id.py
atams/schemas/__init__.py
atams/schemas/response.py
atams/sso/__init__.py
atams/sso/client.py
atams/sso/deps.py
atams/sso/encryption.py
atams/transaction/__init__.py
atams/transaction/manager.py
atams/utils/__init__.py
atams/utils/file_utils.py
atams/utils/import_injector.py
atams/utils/naming.py
atams-1.1.4.dist-info/licenses/LICENSE
atams-1.1.4.dist-info/METADATA
atams-1.1.4.dist-info/WHEEL
atams-1.1.4.dist-info/entry_points.txt
atams-1.1.4.dist-info/top_level.txt
atams-1.1.4.dist-info/RECORD
