Metadata-Version: 2.4
Name: atams
Version: 1.1.4
Summary: Advanced Toolkit for Application Management System - Universal toolkit for AURA projects
Author: ATAMS Team
Author-email: ATAMS Team <atamsindonesia@gmail.com>
License-Expression: MIT
Project-URL: Homepage, https://github.com/atams/atams-toolkit
Project-URL: Documentation, https://atams-toolkit.readthedocs.io
Project-URL: Repository, https://github.com/atams/atams-toolkit
Project-URL: Issues, https://github.com/atams/atams-toolkit/issues
Keywords: fastapi,toolkit,aura,atams,framework,boilerplate
Classifier: Development Status :: 5 - Production/Stable
Classifier: Intended Audience :: Developers
Classifier: Programming Language :: Python :: 3
Classifier: Programming Language :: Python :: 3.9
Classifier: Programming Language :: Python :: 3.10
Classifier: Programming Language :: Python :: 3.11
Classifier: Programming Language :: Python :: 3.12
Classifier: Framework :: FastAPI
Classifier: Topic :: Software Development :: Libraries :: Python Modules
Classifier: Topic :: Software Development :: Code Generators
Requires-Python: >=3.9
License-File: LICENSE
Requires-Dist: fastapi>=0.104.0
Requires-Dist: sqlalchemy>=2.0.0
Requires-Dist: pydantic>=2.0.0
Requires-Dist: pydantic-settings>=2.0.0
Requires-Dist: pycryptodome>=3.19.0
Requires-Dist: httpx>=0.25.0
Requires-Dist: email-validator>=2.0.0
Requires-Dist: typer>=0.9.0
Requires-Dist: rich>=13.0.0
Requires-Dist: jinja2>=3.1.0
Requires-Dist: inflect>=7.0.0
Provides-Extra: dev
Requires-Dist: pytest>=7.4.0; extra == "dev"
Requires-Dist: pytest-asyncio>=0.21.0; extra == "dev"
Requires-Dist: pytest-cov>=4.1.0; extra == "dev"
Requires-Dist: black>=23.0.0; extra == "dev"
Requires-Dist: flake8>=6.0.0; extra == "dev"
Requires-Dist: mypy>=1.0.0; extra == "dev"
Requires-Dist: build>=0.10.0; extra == "dev"
Requires-Dist: twine>=4.0.0; extra == "dev"
Dynamic: author
Dynamic: license-file
Dynamic: requires-python
